JingtongJava11ChuyiFix1/README.md
JingtongJava11ChuyiFix1/__init__.py
JingtongJava11ChuyiFix1/__main__.py
JingtongJava11ChuyiFix1/file.epub
JingtongJava11ChuyiFix1/index.html
JingtongJava11ChuyiFix1/css/__init__.py
JingtongJava11ChuyiFix1/css/annotations.css
JingtongJava11ChuyiFix1/css/main.css
JingtongJava11ChuyiFix1/css/normalize.css
JingtongJava11ChuyiFix1/css/popup.css
JingtongJava11ChuyiFix1/font/__init__.py
JingtongJava11ChuyiFix1/font/fontello.eot
JingtongJava11ChuyiFix1/font/fontello.svg
JingtongJava11ChuyiFix1/font/fontello.ttf
JingtongJava11ChuyiFix1/font/fontello.woff
JingtongJava11ChuyiFix1/img/__init__.py
JingtongJava11ChuyiFix1/img/annotator-glyph-sprite.png
JingtongJava11ChuyiFix1/img/annotator-icon-sprite.png
JingtongJava11ChuyiFix1/img/apple-touch-icon.png
JingtongJava11ChuyiFix1/img/cancelfullscreen.png
JingtongJava11ChuyiFix1/img/close.png
JingtongJava11ChuyiFix1/img/fullscreen.png
JingtongJava11ChuyiFix1/img/loader.gif
JingtongJava11ChuyiFix1/img/menu-icon.png
JingtongJava11ChuyiFix1/img/save.png
JingtongJava11ChuyiFix1/img/saved.png
JingtongJava11ChuyiFix1/img/settings-s.png
JingtongJava11ChuyiFix1/img/settings.png
JingtongJava11ChuyiFix1/img/star.png
JingtongJava11ChuyiFix1/js/__init__.py
JingtongJava11ChuyiFix1/js/epub.js
JingtongJava11ChuyiFix1/js/epub.min.js
JingtongJava11ChuyiFix1/js/epub.min.map
JingtongJava11ChuyiFix1/js/hooks.min.js
JingtongJava11ChuyiFix1/js/hooks.min.map
JingtongJava11ChuyiFix1/js/reader.js
JingtongJava11ChuyiFix1/js/reader.js.map
JingtongJava11ChuyiFix1/js/reader.min.js
JingtongJava11ChuyiFix1/js/reader.min.map
JingtongJava11ChuyiFix1/js/hooks/__init__.py
JingtongJava11ChuyiFix1/js/hooks/extensions/__init__.py
JingtongJava11ChuyiFix1/js/hooks/extensions/highlight.js
JingtongJava11ChuyiFix1/js/libs/__init__.py
JingtongJava11ChuyiFix1/js/libs/jquery.min.js
JingtongJava11ChuyiFix1/js/libs/localforage.min.js
JingtongJava11ChuyiFix1/js/libs/screenfull.js
JingtongJava11ChuyiFix1/js/libs/screenfull.min.js
jingtong_java_11_chuyi_fix1-2025.3.25.1.dist-info/METADATA
jingtong_java_11_chuyi_fix1-2025.3.25.1.dist-info/WHEEL
jingtong_java_11_chuyi_fix1-2025.3.25.1.dist-info/entry_points.txt
jingtong_java_11_chuyi_fix1-2025.3.25.1.dist-info/top_level.txt
jingtong_java_11_chuyi_fix1-2025.3.25.1.dist-info/RECORD
